namextracter/__init__.py
namextracter-0.0.1.dist-info/LICENSE
namextracter-0.0.1.dist-info/METADATA
namextracter-0.0.1.dist-info/WHEEL
namextracter-0.0.1.dist-info/top_level.txt
namextracter-0.0.1.dist-info/RECORD
