Metadata-Version: 2.1
Name: namextracter
Version: 0.0.1
Summary: A lite library for extracting names from text using nltk wordnet
Home-page: https://github.com/frier-sam/namextracter
Author: sam-iau
Author-email: sam-iau@outlook.com
License: UNKNOWN
Platform: UNKNOWN
Classifier: Programming Language :: Python :: 3.6
Classifier: License :: OSI Approved :: MIT License
Classifier: Operating System :: OS Independent
Requires-Dist: nltk (==3.3)
